medussa/__init__.py
medussa/docs.py
medussa/libmedussa.cp37-win_amd64.pyd
medussa/medussa.py
medussa/pink.py
medussa/portaudio.py
medussa/rkit.py
medussa/sndfile.py
medussa/sndfile_formats.py
medussa/symbols.lst
medussa/lib/libsndfile.dll
medussa/lib/portaudio.dll
medussa-2.0.2.dist-info/AUTHORS.md
medussa-2.0.2.dist-info/COPYING.md
medussa-2.0.2.dist-info/METADATA
medussa-2.0.2.dist-info/WHEEL
medussa-2.0.2.dist-info/eager_resources.txt
medussa-2.0.2.dist-info/top_level.txt
medussa-2.0.2.dist-info/RECORD
